minivirt/__main__.py
minivirt/build.py
minivirt/cache.py
minivirt/cli.py
minivirt/configs.py
minivirt/contrib/githubactions.py
minivirt/db.py
minivirt/exceptions.py
minivirt/qemu.py
minivirt/remotes.py
minivirt/utils.py
minivirt/vagrant-private-key
minivirt/vms.py
minivirt-0.1.dist-info/entry_points.txt
minivirt-0.1.dist-info/LICENSE
minivirt-0.1.dist-info/WHEEL
minivirt-0.1.dist-info/METADATA
minivirt-0.1.dist-info/RECORD
