Metadata-Version: 2.1
Name: minivirt
Version: 0.1
Summary: Painless VM management from the CLI
Home-page: https://github.com/mgax/minivirt
Author: Alex Morega
Author-email: alex@grep.ro
Requires-Python: >=3.8,<4.0
Classifier: Programming Language :: Python :: 3
Classifier: Programming Language :: Python :: 3.8
Classifier: Programming Language :: Python :: 3.9
Classifier: Programming Language :: Python :: 3.10
Provides-Extra: devel
Provides-Extra: githubactions
Requires-Dist: PyGithub (>=1.55,<2.0); extra == "githubactions"
Requires-Dist: PyYAML (>=6.0,<7.0)
Requires-Dist: boto3 (>=1.24.87,<2.0.0)
Requires-Dist: click (>=8.1.3,<9.0.0)
Requires-Dist: poetry (>=1.2.1,<2.0.0); extra == "devel"
Requires-Dist: pyngrok (>=5.1.0,<6.0.0); extra == "githubactions"
Requires-Dist: pytest (>=7.1.3,<8.0.0); extra == "devel"
Requires-Dist: waitress (>=2.1.2,<3.0.0); extra == "githubactions"
Project-URL: Repository, https://github.com/mgax/minivirt
